Metadata-Version: 2.1
Name: E2Yaml
Version: 0.4.2
Summary: An Environment Variable to Yaml Converter
Home-page: https://github.com/josephp27/E2Yaml
Author: Joseph Procopio
Author-email: josephp27@live.com
License: MIT
Download-URL: https://github.com/josephp27/E2Yaml/archive/0.4.2.tar.gz
Keywords: Yaml,Converter,Environment,Variables
Platform: UNKNOWN
Classifier: Programming Language :: Python :: 3
Classifier: License :: OSI Approved :: MIT License
Classifier: Operating System :: OS Independent
